pyframe3dd/__init__.py
pyframe3dd/pyframe3dd.py
pyframe3dd/_pyframe3dd.dylib
wisdem_pyframe3dd-1.1.1.dist-info/RECORD
wisdem_pyframe3dd-1.1.1.dist-info/WHEEL
wisdem_pyframe3dd-1.1.1.dist-info/METADATA
