Metadata-Version: 2.1
Name: WISDEM-pyFrame3DD
Version: 1.1.1
Summary: Python bindings to Frame3DD, a code for static and dynamic structural analysis of 2D and 3D frames and trusses, with permission from Prof Henri Gavin
Keywords: wind,turbine,mdao,design,optimization
Author-Email: NREL WISDEM Team <systems.engineering@nrel.gov>
Maintainer-Email: NREL WISDEM Team <systems.engineering@nrel.gov>
License: GPL-3.0-only
Classifier: Development Status :: 4 - Beta
Classifier: Intended Audience :: Science/Research
Classifier: Topic :: Scientific/Engineering
Classifier: License :: OSI Approved :: GNU General Public License v3 (GPLv3)
Classifier: Programming Language :: Python :: 3
Classifier: Programming Language :: Python :: 3.9
Classifier: Programming Language :: Python :: 3.10
Classifier: Programming Language :: Python :: 3.11
Classifier: Programming Language :: Python :: 3.12
Classifier: Programming Language :: Python :: 3 :: Only
Classifier: Programming Language :: C
Classifier: Operating System :: Microsoft :: Windows
Classifier: Operating System :: POSIX :: Linux
Classifier: Operating System :: POSIX
Classifier: Operating System :: Unix
Classifier: Operating System :: MacOS
Project-URL: Homepage, https://github.com/WISDEM/pyFrame3DD
Project-URL: Project, https://frame3dd.sourceforge.net
Requires-Python: >=3.9
Requires-Dist: numpy
Requires-Dist: meson; extra == "dev"
Requires-Dist: ninja; extra == "dev"
Requires-Dist: pytest; extra == "test"
Provides-Extra: dev
Provides-Extra: test
